[
	{
		"id": 2,
		"priority": 2,
		"action": {
			"type": "modifyHeaders",
			"responseHeaders": [
                {
					"header": "Permissions-Policy",
					"operation": "set",
					"value": "accelerometer=(self), attribution-reporting=(), autoplay=(), bluetooth=(), camera=(self), ch-device-memory=(), ch-downlink=(), ch-dpr=(), ch-ect=(), ch-rtt=(), ch-save-data=(), ch-ua-arch=(), ch-ua-bitness=(), ch-viewport-height=(), ch-viewport-width=(), ch-width=(), clipboard-read=(), clipboard-write=(self), encrypted-media=(), fullscreen=(self), gamepad=(), geolocation=(self), gyroscope=(self), hid=(), idle-detection=(), keyboard-map=(), local-fonts=(), magnetometer=(), microphone=(self), midi=(), otp-credentials=(), payment=(), picture-in-picture=(self), publickey-credentials-get=(), screen-wake-lock=(), serial=(), usb=(), window-management=(), xr-spatial-tracking=();"
				}
			]
		},
		"condition": {
			"urlFilter": "*://*.instagram.com/*",
            "resourceTypes": ["main_frame", "sub_frame", "stylesheet", "script", "image", "font", "object", "xmlhttprequest", "ping", "csp_report", "media", "websocket", "webtransport", "webbundle", "other"]
		}
	}
]
